{"queryCost": 1, "latitude": 45.0780983, "longitude": -83.56030273, "resolvedAddress": "45.0780983, -83.56030273", "address": "45.0780983, -83.56030273", "timezone": "America/Detroit", "tzoffset": -5.0, "days": [{"datetime": "2020-01-04", "datetimeEpoch": 1578114000, "tempmax": 0.0, "tempmin": -2.1, "temp": -1.1, "feelslikemax": -2.5, "feelslikemin": -6.2, "feelslike": -4.6, "dew": -4.6, "humidity": 77.34, "precip": 0.5, "precipprob": null, "precipcover": 4.17, "preciptype": null, "snow": 0.02, "snowdepth": 3.02, "windgust": 31.7, "windspeed": 13.0, "winddir": 301.2, "pressure": 1012.0, "cloudcover": 94.5, "visibility": 15.5, "solarradiation": null, "solarenergy": null, "sunrise": "08:12:52", "sunriseEpoch": 1578143572, "sunset": "17:05:29", "sunsetEpoch": 1578175529, "moonphase": 0.31, "conditions": "Snow, Overcast", "icon": "snow", "stations": ["72741754825", "KAPN", "KOSC", "72639094849", "APNM4"], "source": "obs", "hours": null}], "stations": {"72741754825": {"distance": 41650.0, "latitude": 45.407, "longitude": -83.813, "useCount": 0, "id": "72741754825", "name": "ROGERS CITY PRESQUE ISLE CO AIRPORT, MI US", "quality": 50, "contribution": 0.0}, "72639094849": {"distance": 792.0, "latitude": 45.072, "longitude": -83.564, "useCount": 0, "id": "72639094849", "name": "ALPENA CO REGIONAL AIRPORT, MI US", "quality": 100, "contribution": 0.0}, "KAPN": {"distance": 1181.0, "latitude": 45.07, "longitude": -83.57, "useCount": 0, "id": "KAPN", "name": "KAPN", "quality": 100, "contribution": 0.0}, "KOSC": {"distance": 71058.0, "latitude": 44.45, "longitude": -83.4, "useCount": 0, "id": "KOSC", "name": "KOSC", "quality": 100, "contribution": 0.0}, "APNM4": {"distance": 9220.0, "latitude": 45.05, "longitude": -83.45, "useCount": 0, "id": "APNM4", "name": "APNM4 (maritime)", "quality": 50, "contribution": 0.0}}}