{"queryCost": 1, "latitude": 42.908001, "longitude": -106.463997, "resolvedAddress": "42.908001, -106.463997", "address": "42.908001, -106.463997", "timezone": "America/Denver", "tzoffset": -7.0, "days": [{"datetime": "2019-02-21", "datetimeEpoch": 1550732400, "tempmax": -6.2, "tempmin": -18.3, "temp": -11.2, "feelslikemax": -14.3, "feelslikemin": -24.0, "feelslike": -18.0, "dew": -13.8, "humidity": 81.79, "precip": 1.2, "precipprob": null, "precipcover": 16.67, "preciptype": null, "snow": 3.12, "snowdepth": 6.12, "windgust": null, "windspeed": 33.5, "winddir": 137.5, "pressure": 1016.7, "cloudcover": 64.8, "visibility": 10.6, "solarradiation": 200.4, "solarenergy": 7.9, "sunrise": "06:54:35", "sunriseEpoch": 1550757275, "sunset": "17:44:59", "sunsetEpoch": 1550796299, "moonphase": 0.53, "conditions": "Snow, Partially cloudy", "icon": "snow", "stations": ["72569024089", "KCPR"], "source": "obs", "hours": null}], "stations": {"72569024089": {"distance": 1398.0, "latitude": 42.898, "longitude": -106.474, "useCount": 0, "id": "72569024089", "name": "CASPER NATRONA CO AIRPORT, WY US", "quality": 100, "contribution": 0.0}, "KCPR": {"distance": 1423.0, "latitude": 42.92, "longitude": -106.47, "useCount": 0, "id": "KCPR", "name": "KCPR", "quality": 100, "contribution": 0.0}}}