{"queryCost": 1, "latitude": 38.94449997, "longitude": -77.45580292, "resolvedAddress": "38.94449997, -77.45580292", "address": "38.94449997, -77.45580292", "timezone": "America/New_York", "tzoffset": -5.0, "days": [{"datetime": "2020-01-04", "datetimeEpoch": 1578114000, "tempmax": 14.3, "tempmin": 7.2, "temp": 10.8, "feelslikemax": 14.3, "feelslikemin": 2.6, "feelslike": 9.9, "dew": 8.6, "humidity": 86.95, "precip": 13.06, "precipprob": null, "precipcover": 45.83, "preciptype": null, "snow": 0.0, "snowdepth": 0.0, "windgust": 50.0, "windspeed": 38.8, "winddir": 195.0, "pressure": 1004.6, "cloudcover": 69.0, "visibility": 9.5, "solarradiation": 270.7, "solarenergy": 19.5, "sunrise": "07:28:56", "sunriseEpoch": 1578140936, "sunset": "17:00:31", "sunsetEpoch": 1578175231, "moonphase": 0.31, "conditions": "Rain, Partially cloudy", "icon": "rain", "stations": ["72405503714", "72403603710", "KIAD", "72403093738", "KJYO", "KHEF"], "source": "obs", "hours": null}], "stations": {"72405503714": {"distance": 17250.0, "latitude": 39.078, "longitude": -77.557, "useCount": 0, "id": "72405503714", "name": "LEESBURG EXECUTIVE AIRPORT, VA US", "quality": 98, "contribution": 0.0}, "72403603710": {"distance": 25366.0, "latitude": 38.721, "longitude": -77.515, "useCount": 0, "id": "72403603710", "name": "MANASSAS REGIONAL DAVIS FIELD AIRPORT, VA US", "quality": 100, "contribution": 0.0}, "KIAD": {"distance": 792.0, "latitude": 38.95, "longitude": -77.45, "useCount": 0, "id": "KIAD", "name": "KIAD", "quality": 100, "contribution": 0.0}, "72403093738": {"distance": 1298.0, "latitude": 38.935, "longitude": -77.447, "useCount": 0, "id": "72403093738", "name": "WASHINGTON DULLES INTERNATIONAL AIRPORT, VA US", "quality": 100, "contribution": 0.0}, "KJYO": {"distance": 17571.0, "latitude": 39.08, "longitude": -77.56, "useCount": 0, "id": "KJYO", "name": "KJYO", "quality": 98, "contribution": 0.0}, "KHEF": {"distance": 25604.0, "latitude": 38.72, "longitude": -77.52, "useCount": 0, "id": "KHEF", "name": "MANASSAS MUNI, VA", "quality": 100, "contribution": 0.0}}}