{"queryCost": 1, "latitude": 40.639801, "longitude": -73.7789, "resolvedAddress": "40.639801, -73.7789", "address": "40.639801, -73.7789", "timezone": "America/New_York", "tzoffset": -5.0, "days": [{"datetime": "2018-01-05", "datetimeEpoch": 1515128400, "tempmax": -7.1, "tempmin": -12.1, "temp": -10.2, "feelslikemax": -17.8, "feelslikemin": -23.9, "feelslike": -21.1, "dew": -19.0, "humidity": 49.72, "precip": 0.78, "precipprob": null, "precipcover": 4.17, "preciptype": null, "snow": 5.98, "snowdepth": 20.21, "windgust": 74.1, "windspeed": 49.9, "winddir": 288.3, "pressure": 1009.5, "cloudcover": 32.8, "visibility": 16.0, "solarradiation": null, "solarenergy": null, "sunrise": "07:19:10", "sunriseEpoch": 1515154750, "sunset": "16:42:12", "sunsetEpoch": 1515188532, "moonphase": 0.58, "conditions": "Snow, Partially cloudy", "icon": "snow", "stations": ["72055399999", "KJFK", "74486094789", "KLGA", "KJRB", "72503014732"], "source": "obs", "hours": null}], "stations": {"72055399999": {"distance": 20595.0, "latitude": 40.701, "longitude": -74.009, "useCount": 0, "id": "72055399999", "name": "PORT AUTH DOWNTN MANHATTAN WALL ST HEL, NY US", "quality": 100, "contribution": 0.0}, "KJFK": {"distance": 1139.0, "latitude": 40.65, "longitude": -73.78, "useCount": 0, "id": "KJFK", "name": "KJFK", "quality": 100, "contribution": 0.0}, "74486094789": {"distance": 1261.0, "latitude": 40.639, "longitude": -73.764, "useCount": 0, "id": "74486094789", "name": "JFK INTERNATIONAL AIRPORT, NY US", "quality": 100, "contribution": 0.0}, "KLGA": {"distance": 17734.0, "latitude": 40.77, "longitude": -73.9, "useCount": 0, "id": "KLGA", "name": "KLGA", "quality": 100, "contribution": 0.0}, "KJRB": {"distance": 20595.0, "latitude": 40.701, "longitude": -74.009, "useCount": 0, "id": "KJRB", "name": "Downtown Manhattan/wall St, New York", "quality": 100, "contribution": 0.0}, "72503014732": {"distance": 17740.0, "latitude": 40.779, "longitude": -73.88, "useCount": 0, "id": "72503014732", "name": "LAGUARDIA AIRPORT, NY US", "quality": 100, "contribution": 0.0}}}