{"queryCost": 1, "latitude": 40.639801, "longitude": -73.7789, "resolvedAddress": "40.639801, -73.7789", "address": "40.639801, -73.7789", "timezone": "America/New_York", "tzoffset": -4.0, "days": [{"datetime": "2019-08-07", "datetimeEpoch": 1565150400, "tempmax": 28.9, "tempmin": 21.2, "temp": 24.0, "feelslikemax": 32.8, "feelslikemin": 21.2, "feelslike": 24.5, "dew": 22.7, "humidity": 92.72, "precip": 25.47, "precipprob": null, "precipcover": 33.33, "preciptype": null, "snow": 0.0, "snowdepth": 0.0, "windgust": 53.6, "windspeed": 35.2, "winddir": 183.5, "pressure": 1009.8, "cloudcover": 60.1, "visibility": 14.4, "solarradiation": 310.4, "solarenergy": 14.5, "sunrise": "05:57:28", "sunriseEpoch": 1565171848, "sunset": "20:03:42", "sunsetEpoch": 1565222622, "moonphase": 0.24, "conditions": "Rain, Partially cloudy", "icon": "rain", "stations": ["72055399999", "KJFK", "74486094789", "KLGA", "KJRB", "72503014732"], "source": "obs", "hours": null}], "stations": {"72055399999": {"distance": 20595.0, "latitude": 40.701, "longitude": -74.009, "useCount": 0, "id": "72055399999", "name": "PORT AUTH DOWNTN MANHATTAN WALL ST HEL, NY US", "quality": 100, "contribution": 0.0}, "KJFK": {"distance": 1139.0, "latitude": 40.65, "longitude": -73.78, "useCount": 0, "id": "KJFK", "name": "KJFK", "quality": 100, "contribution": 0.0}, "74486094789": {"distance": 1261.0, "latitude": 40.639, "longitude": -73.764, "useCount": 0, "id": "74486094789", "name": "JFK INTERNATIONAL AIRPORT, NY US", "quality": 100, "contribution": 0.0}, "KLGA": {"distance": 17734.0, "latitude": 40.77, "longitude": -73.9, "useCount": 0, "id": "KLGA", "name": "KLGA", "quality": 100, "contribution": 0.0}, "KJRB": {"distance": 20595.0, "latitude": 40.701, "longitude": -74.009, "useCount": 0, "id": "KJRB", "name": "Downtown Manhattan/wall St, New York", "quality": 100, "contribution": 0.0}, "72503014732": {"distance": 17740.0, "latitude": 40.779, "longitude": -73.88, "useCount": 0, "id": "72503014732", "name": "LAGUARDIA AIRPORT, NY US", "quality": 100, "contribution": 0.0}}}