{"queryCost": 1, "latitude": 36.08010101, "longitude": -115.1520004, "resolvedAddress": "36.08010101, -115.1520004", "address": "36.08010101, -115.1520004", "timezone": "America/Los_Angeles", "tzoffset": -7.0, "days": [{"datetime": "2019-10-30", "datetimeEpoch": 1572418800, "tempmax": 11.2, "tempmin": 2.2, "temp": 6.7, "feelslikemax": 11.2, "feelslikemin": -2.5, "feelslike": 4.0, "dew": -18.5, "humidity": 15.52, "precip": 0.0, "precipprob": null, "precipcover": 0.0, "preciptype": null, "snow": 0.0, "snowdepth": 0.0, "windgust": 55.1, "windspeed": 31.6, "winddir": 91.5, "pressure": 1029.1, "cloudcover": 0.0, "visibility": 16.0, "solarradiation": 384.2, "solarenergy": 16.6, "sunrise": "07:01:10", "sunriseEpoch": 1572444070, "sunset": "17:46:50", "sunsetEpoch": 1572482810, "moonphase": 0.04, "conditions": "Clear", "icon": "wind", "stations": ["KLAS", "74614023112", "KLSV", "72386023169", "KVGT", "72484653123"], "source": "obs", "hours": null}], "stations": {"KLAS": {"distance": 1619.0, "latitude": 36.08, "longitude": -115.17, "useCount": 0, "id": "KLAS", "name": "KLAS", "quality": 100, "contribution": 0.0}, "74614023112": {"distance": 21727.0, "latitude": 36.25, "longitude": -115.033, "useCount": 0, "id": "74614023112", "name": "LAS VEGAS NELLIS AFB, NV US", "quality": 96, "contribution": 0.0}, "KLSV": {"distance": 19047.0, "latitude": 36.22, "longitude": -115.03, "useCount": 0, "id": "KLSV", "name": "KLSV", "quality": 99, "contribution": 0.0}, "72386023169": {"distance": 1346.0, "latitude": 36.072, "longitude": -115.163, "useCount": 0, "id": "72386023169", "name": "MCCARRAN INTERNATIONAL AIRPORT, NV US", "quality": 100, "contribution": 0.0}, "KVGT": {"distance": 15090.0, "latitude": 36.21, "longitude": -115.2, "useCount": 0, "id": "KVGT", "name": "KVGT", "quality": 100, "contribution": 0.0}, "72484653123": {"distance": 15174.0, "latitude": 36.212, "longitude": -115.196, "useCount": 0, "id": "72484653123", "name": "LAS VEGAS AIR TERMINAL, NV US", "quality": 100, "contribution": 0.0}}}