{"queryCost": 1, "latitude": 36.89459991455078, "longitude": -76.20120239257812, "resolvedAddress": "36.89459991455078, -76.20120239257812", "address": "36.89459991455078, -76.20120239257812", "timezone": "America/New_York", "tzoffset": -4.0, "days": [{"datetime": "2018-07-18", "datetimeEpoch": 1531886400, "tempmax": 29.3, "tempmin": 22.8, "temp": 26.4, "feelslikemax": 31.1, "feelslikemin": 22.8, "feelslike": 26.9, "dew": 20.1, "humidity": 70.65, "precip": 0.0, "precipprob": null, "precipcover": 4.17, "preciptype": null, "snow": 0.0, "snowdepth": 0.0, "windgust": 38.8, "windspeed": 24.1, "winddir": 167.6, "pressure": 1012.7, "cloudcover": 27.2, "visibility": 16.0, "solarradiation": 467.2, "solarenergy": 25.2, "sunrise": "05:59:26", "sunriseEpoch": 1531907966, "sunset": "20:22:19", "sunsetEpoch": 1531959739, "moonphase": 0.18, "conditions": "Partially cloudy", "icon": "partly-cloudy-day", "stations": ["KNGU", "72307513769", "72308513750", "KNTU", "KORF", "72308013737"], "source": "obs", "hours": null}], "stations": {"KNGU": {"distance": 8045.0, "latitude": 36.93, "longitude": -76.28, "useCount": 0, "id": "KNGU", "name": "KNGU", "quality": 100, "contribution": 0.0}, "72307513769": {"distance": 17288.0, "latitude": 36.817, "longitude": -76.033, "useCount": 0, "id": "72307513769", "name": "OCEANA NAS, VA US", "quality": 100, "contribution": 0.0}, "72308513750": {"distance": 9181.0, "latitude": 36.938, "longitude": -76.289, "useCount": 0, "id": "72308513750", "name": "NORFOLK NAS, VA US", "quality": 100, "contribution": 0.0}, "KNTU": {"distance": 17364.0, "latitude": 36.82, "longitude": -76.03, "useCount": 0, "id": "KNTU", "name": "KNTU", "quality": 100, "contribution": 0.0}, "KORF": {"distance": 611.0, "latitude": 36.9, "longitude": -76.2, "useCount": 0, "id": "KORF", "name": "KORF", "quality": 100, "contribution": 0.0}, "72308013737": {"distance": 1257.0, "latitude": 36.903, "longitude": -76.192, "useCount": 0, "id": "72308013737", "name": "NORFOLK INTERNATIONAL AIRPORT, VA US", "quality": 100, "contribution": 0.0}}}