{"queryCost": 1, "latitude": 42.9098014831543, "longitude": -112.59600067138672, "resolvedAddress": "42.9098014831543, -112.59600067138672", "address": "42.9098014831543, -112.59600067138672", "timezone": "America/Boise", "tzoffset": -7.0, "days": [{"datetime": "2020-01-06", "datetimeEpoch": 1578294000, "tempmax": 3.3, "tempmin": -3.3, "temp": -0.1, "feelslikemax": -2.0, "feelslikemin": -10.8, "feelslike": -6.2, "dew": -5.7, "humidity": 66.6, "precip": 0.0, "precipprob": null, "precipcover": 0.0, "preciptype": null, "snow": 1.0, "snowdepth": 3.0, "windgust": 51.8, "windspeed": 37.1, "winddir": 215.8, "pressure": 1031.9, "cloudcover": 47.0, "visibility": 16.0, "solarradiation": 125.1, "solarenergy": 5.0, "sunrise": "08:01:27", "sunriseEpoch": 1578322887, "sunset": "17:11:03", "sunsetEpoch": 1578355863, "moonphase": 0.4, "conditions": "Partially cloudy", "icon": "snow", "stations": ["KPIH", "CPRL", "KIDA", "72578524145", "72578024156"], "source": "obs", "hours": null}], "stations": {"CPRL": {"distance": 19808.0, "latitude": 42.78, "longitude": -112.43, "useCount": 0, "id": "CPRL", "name": "CPRL", "quality": 45, "contribution": 0.0}, "KIDA": {"distance": 80219.0, "latitude": 43.52, "longitude": -112.07, "useCount": 0, "id": "KIDA", "name": "IDAHO FALLS/FANG, ID", "quality": 100, "contribution": 0.0}, "72578524145": {"distance": 80385.0, "latitude": 43.519, "longitude": -112.064, "useCount": 0, "id": "72578524145", "name": "IDAHO FALLS FANNING FIELD, ID US", "quality": 100, "contribution": 0.0}, "KPIH": {"distance": 1181.0, "latitude": 42.92, "longitude": -112.6, "useCount": 0, "id": "KPIH", "name": "KPIH", "quality": 100, "contribution": 0.0}, "72578024156": {"distance": 2344.0, "latitude": 42.92, "longitude": -112.571, "useCount": 0, "id": "72578024156", "name": "POCATELLO REGIONAL AIRPORT, ID US", "quality": 100, "contribution": 0.0}}}