{"queryCost": 1, "latitude": 33.8297004699707, "longitude": -116.50700378417969, "resolvedAddress": "33.8297004699707, -116.50700378417969", "address": "33.8297004699707, -116.50700378417969", "timezone": "America/Los_Angeles", "tzoffset": -7.0, "days": [{"datetime": "2019-04-09", "datetimeEpoch": 1554793200, "tempmax": 34.4, "tempmin": 20.7, "temp": 27.2, "feelslikemax": 31.8, "feelslikemin": 20.7, "feelslike": 26.3, "dew": 2.9, "humidity": 23.59, "precip": 0.0, "precipprob": null, "precipcover": 0.0, "preciptype": null, "snow": 0.0, "snowdepth": 0.0, "windgust": 74.0, "windspeed": 50.0, "winddir": 270.5, "pressure": 1009.7, "cloudcover": 0.0, "visibility": 16.0, "solarradiation": 475.6, "solarenergy": 24.0, "sunrise": "06:23:01", "sunriseEpoch": 1554816181, "sunset": "19:12:42", "sunsetEpoch": 1554862362, "moonphase": 0.08, "conditions": "Clear", "icon": "wind", "stations": ["KL35", "KPSP", "74718703104", "72286893138", "A0685400115"], "source": "obs", "hours": null}], "stations": {"KL35": {"distance": 57919.0, "latitude": 34.26, "longitude": -116.86, "useCount": 0, "id": "KL35", "name": "KL35", "quality": 100, "contribution": 0.0}, "KPSP": {"distance": 649.0, "latitude": 33.83, "longitude": -116.5, "useCount": 0, "id": "KPSP", "name": "KPSP", "quality": 100, "contribution": 0.0}, "74718703104": {"distance": 39354.0, "latitude": 33.627, "longitude": -116.159, "useCount": 0, "id": "74718703104", "name": "DESERT RESORTS REGIONAL AIRPORT, CA US", "quality": 96, "contribution": 0.0}, "72286893138": {"distance": 880.0, "latitude": 33.822, "longitude": -116.504, "useCount": 0, "id": "72286893138", "name": "PALM SPRINGS ASOS, CA US", "quality": 100, "contribution": 0.0}, "A0685400115": {"distance": 57980.0, "latitude": 34.264, "longitude": -116.854, "useCount": 0, "id": "A0685400115", "name": "BIG BEAR CITY AIRPORT, CA US", "quality": 100, "contribution": 0.0}}}