{"queryCost": 1, "latitude": 40.8493003845, "longitude": -77.84870147710001, "resolvedAddress": "40.8493003845, -77.84870147710001", "address": "40.8493003845, -77.84870147710001", "timezone": "America/New_York", "tzoffset": -5.0, "days": [{"datetime": "2020-01-07", "datetimeEpoch": 1578373200, "tempmax": 1.8, "tempmin": -4.2, "temp": -0.9, "feelslikemax": 0.0, "feelslikemin": -6.4, "feelslike": -2.2, "dew": -4.2, "humidity": 80.18, "precip": 2.08, "precipprob": null, "precipcover": 16.67, "preciptype": null, "snow": 2.22, "snowdepth": 2.22, "windgust": 35.3, "windspeed": 24.1, "winddir": 238.3, "pressure": 1015.9, "cloudcover": 38.6, "visibility": 11.4, "solarradiation": 18.5, "solarenergy": 1.5, "uvindex": 1.0, "sunrise": "07:35:58", "sunriseEpoch": 1578400558, "sunset": "16:59:20", "sunsetEpoch": 1578434360, "moonphase": 0.44, "conditions": "Snow, Partially cloudy", "description": "Partly cloudly with late afternoon rain or snow.", "icon": "snow", "stations": ["KUNV", "99999954783", "72511954792", "KAOO", "KFIG", "72512614736"], "source": "obs", "hours": null}], "stations": {"KUNV": {"distance": 737.0, "latitude": 40.85, "longitude": -77.84, "useCount": 0, "id": "KUNV", "name": "KUNV", "quality": 99, "contribution": 0.0}, "99999954783": {"distance": 15942.0, "latitude": 40.72, "longitude": -77.93, "useCount": 0, "id": "99999954783", "name": null, "quality": 46, "contribution": 0.0}, "72511954792": {"distance": 52189.0, "latitude": 41.047, "longitude": -78.412, "useCount": 0, "id": "72511954792", "name": "CLEARFIELD LAWRENCE AIRPORT, PA US", "quality": 100, "contribution": 0.0}, "KAOO": {"distance": 73471.0, "latitude": 40.29, "longitude": -78.31, "useCount": 0, "id": "KAOO", "name": "KAOO", "quality": 100, "contribution": 0.0}, "KFIG": {"distance": 52214.0, "latitude": 41.05, "longitude": -78.41, "useCount": 0, "id": "KFIG", "name": "KFIG", "quality": 100, "contribution": 0.0}, "72512614736": {"distance": 73337.0, "latitude": 40.296, "longitude": -78.32, "useCount": 0, "id": "72512614736", "name": "ALTOONA BLAIR CO AIRPORT, PA US", "quality": 100, "contribution": 0.0}}}