{"queryCost": 1, "latitude": 43.11119842529297, "longitude": -76.1063003540039, "resolvedAddress": "43.11119842529297, -76.1063003540039", "address": "43.11119842529297, -76.1063003540039", "timezone": "America/New_York", "tzoffset": -5.0, "days": [{"datetime": "2020-01-01", "datetimeEpoch": 1577854800, "tempmax": 1.7, "tempmin": -1.2, "temp": 0.4, "feelslikemax": -3.4, "feelslikemin": -7.0, "feelslike": -5.3, "dew": -5.6, "humidity": 64.32, "precip": 0.0, "precipprob": null, "precipcover": 0.0, "preciptype": null, "snow": 1.04, "snowdepth": 3.0, "windgust": 51.8, "windspeed": 35.3, "winddir": 248.8, "pressure": 1005.8, "cloudcover": 95.6, "visibility": 15.9, "solarradiation": 65.9, "solarenergy": 2.1, "sunrise": "07:36:13", "sunriseEpoch": 1577882173, "sunset": "16:39:39", "sunsetEpoch": 1577914779, "moonphase": 0.17, "conditions": "Overcast", "icon": "snow", "stations": ["KSYR", "72519014771", "72514654773", "KFZY", "72519664775", "KRME"], "source": "obs", "hours": null}], "stations": {"KSYR": {"distance": 1483.0, "latitude": 43.12, "longitude": -76.12, "useCount": 0, "id": "KSYR", "name": "KSYR", "quality": 100, "contribution": 0.0}, "72519014771": {"distance": 203.0, "latitude": 43.111, "longitude": -76.104, "useCount": 0, "id": "72519014771", "name": "SYRACUSE HANCOCK INTERNATIONAL AIRPORT, NY US", "quality": 100, "contribution": 0.0}, "72514654773": {"distance": 34854.0, "latitude": 43.35, "longitude": -76.385, "useCount": 0, "id": "72514654773", "name": "FULTON OSWEGO CO AIRPORT, NY US", "quality": 100, "contribution": 0.0}, "KFZY": {"distance": 35159.0, "latitude": 43.35, "longitude": -76.39, "useCount": 0, "id": "KFZY", "name": "KFZY", "quality": 100, "contribution": 0.0}, "72519664775": {"distance": 58022.0, "latitude": 43.234, "longitude": -75.412, "useCount": 0, "id": "72519664775", "name": "ROME GRIFFISS AIRFIELD, NY US", "quality": 100, "contribution": 0.0}, "KRME": {"distance": 58848.0, "latitude": 43.23, "longitude": -75.4, "useCount": 0, "id": "KRME", "name": "KRME", "quality": 100, "contribution": 0.0}}}